{"nodes": [{"id": "e_work_abt_abt_src_repositories_permission_repo_rs", "label": "permission_repo.rs", "file_type": "code", "source_file": "E:\\work\\abt\\abt\\src\\repositories\\permission_repo.rs", "source_location": "L1"}, {"id": "repositories_permission_repo_permissionrepo", "label": "PermissionRepo", "file_type": "code", "source_file": "E:\\work\\abt\\abt\\src\\repositories\\permission_repo.rs", "source_location": "L7"}, {"id": "repositories_permission_repo_permissionrepo_is_super_admin", "label": ".is_super_admin()", "file_type": "code", "source_file": "E:\\work\\abt\\abt\\src\\repositories\\permission_repo.rs", "source_location": "L11"}, {"id": "repositories_permission_repo_permissionrepo_get_user_permission_codes", "label": ".get_user_permission_codes()", "file_type": "code", "source_file": "E:\\work\\abt\\abt\\src\\repositories\\permission_repo.rs", "source_location": "L22"}, {"id": "repositories_permission_repo_permissionrepo_check_permission", "label": ".check_permission()", "file_type": "code", "source_file": "E:\\work\\abt\\abt\\src\\repositories\\permission_repo.rs", "source_location": "L39"}, {"id": "repositories_permission_repo_permissionrepo_insert_audit_log", "label": ".insert_audit_log()", "file_type": "code", "source_file": "E:\\work\\abt\\abt\\src\\repositories\\permission_repo.rs", "source_location": "L70"}, {"id": "repositories_permission_repo_permissionrepo_list_audit_logs", "label": ".list_audit_logs()", "file_type": "code", "source_file": "E:\\work\\abt\\abt\\src\\repositories\\permission_repo.rs", "source_location": "L90"}], "edges": [{"source": "e_work_abt_abt_src_repositories_permission_repo_rs", "target": "result", "relation": "imports_from", "confidence": "EXTRACTED", "source_file": "E:\\work\\abt\\abt\\src\\repositories\\permission_repo.rs", "source_location": "L1", "weight": 1.0, "context": "import"}, {"source": "e_work_abt_abt_src_repositories_permission_repo_rs", "target": "pgpool", "relation": "imports_from", "confidence": "EXTRACTED", "source_file": "E:\\work\\abt\\abt\\src\\repositories\\permission_repo.rs", "source_location": "L2", "weight": 1.0, "context": "import"}, {"source": "e_work_abt_abt_src_repositories_permission_repo_rs", "target": "auditlog", "relation": "imports_from", "confidence": "EXTRACTED", "source_file": "E:\\work\\abt\\abt\\src\\repositories\\permission_repo.rs", "source_location": "L4", "weight": 1.0, "context": "import"}, {"source": "e_work_abt_abt_src_repositories_permission_repo_rs", "target": "executor", "relation": "imports_from", "confidence": "EXTRACTED", "source_file": "E:\\work\\abt\\abt\\src\\repositories\\permission_repo.rs", "source_location": "L5", "weight": 1.0, "context": "import"}, {"source": "e_work_abt_abt_src_repositories_permission_repo_rs", "target": "repositories_permission_repo_permissionrepo", "relation": "contains", "confidence": "EXTRACTED", "source_file": "E:\\work\\abt\\abt\\src\\repositories\\permission_repo.rs", "source_location": "L7", "weight": 1.0}, {"source": "repositories_permission_repo_permissionrepo", "target": "repositories_permission_repo_permissionrepo_is_super_admin", "relation": "method", "confidence": "EXTRACTED", "source_file": "E:\\work\\abt\\abt\\src\\repositories\\permission_repo.rs", "source_location": "L11", "weight": 1.0}, {"source": "repositories_permission_repo_permissionrepo", "target": "repositories_permission_repo_permissionrepo_get_user_permission_codes", "relation": "method", "confidence": "EXTRACTED", "source_file": "E:\\work\\abt\\abt\\src\\repositories\\permission_repo.rs", "source_location": "L22", "weight": 1.0}, {"source": "repositories_permission_repo_permissionrepo", "target": "repositories_permission_repo_permissionrepo_check_permission", "relation": "method", "confidence": "EXTRACTED", "source_file": "E:\\work\\abt\\abt\\src\\repositories\\permission_repo.rs", "source_location": "L39", "weight": 1.0}, {"source": "repositories_permission_repo_permissionrepo", "target": "repositories_permission_repo_permissionrepo_insert_audit_log", "relation": "method", "confidence": "EXTRACTED", "source_file": "E:\\work\\abt\\abt\\src\\repositories\\permission_repo.rs", "source_location": "L70", "weight": 1.0}, {"source": "repositories_permission_repo_permissionrepo", "target": "repositories_permission_repo_permissionrepo_list_audit_logs", "relation": "method", "confidence": "EXTRACTED", "source_file": "E:\\work\\abt\\abt\\src\\repositories\\permission_repo.rs", "source_location": "L90", "weight": 1.0}, {"source": "repositories_permission_repo_permissionrepo_check_permission", "target": "repositories_permission_repo_permissionrepo_is_super_admin", "relation": "calls", "context": "call", "confidence": "EXTRACTED", "source_file": "E:\\work\\abt\\abt\\src\\repositories\\permission_repo.rs", "source_location": "L45", "weight": 1.0}], "raw_calls": [{"caller_nid": "repositories_permission_repo_permissionrepo_is_super_admin", "callee": "fetch_optional", "is_member_call": true, "source_file": "E:\\work\\abt\\abt\\src\\repositories\\permission_repo.rs", "source_location": "L12"}, {"caller_nid": "repositories_permission_repo_permissionrepo_is_super_admin", "callee": "unwrap_or", "is_member_call": true, "source_file": "E:\\work\\abt\\abt\\src\\repositories\\permission_repo.rs", "source_location": "L18"}, {"caller_nid": "repositories_permission_repo_permissionrepo_get_user_permission_codes", "callee": "fetch_all", "is_member_call": true, "source_file": "E:\\work\\abt\\abt\\src\\repositories\\permission_repo.rs", "source_location": "L23"}, {"caller_nid": "repositories_permission_repo_permissionrepo_get_user_permission_codes", "callee": "bind", "is_member_call": true, "source_file": "E:\\work\\abt\\abt\\src\\repositories\\permission_repo.rs", "source_location": "L23"}, {"caller_nid": "repositories_permission_repo_permissionrepo_get_user_permission_codes", "callee": "into_iter", "is_member_call": true, "source_file": "E:\\work\\abt\\abt\\src\\repositories\\permission_repo.rs", "source_location": "L35"}, {"caller_nid": "repositories_permission_repo_permissionrepo_check_permission", "callee": "fetch_one", "is_member_call": true, "source_file": "E:\\work\\abt\\abt\\src\\repositories\\permission_repo.rs", "source_location": "L49"}, {"caller_nid": "repositories_permission_repo_permissionrepo_check_permission", "callee": "unwrap_or", "is_member_call": true, "source_file": "E:\\work\\abt\\abt\\src\\repositories\\permission_repo.rs", "source_location": "L67"}, {"caller_nid": "repositories_permission_repo_permissionrepo_insert_audit_log", "callee": "execute", "is_member_call": true, "source_file": "E:\\work\\abt\\abt\\src\\repositories\\permission_repo.rs", "source_location": "L71"}, {"caller_nid": "repositories_permission_repo_permissionrepo_list_audit_logs", "callee": "fetch_all", "is_member_call": true, "source_file": "E:\\work\\abt\\abt\\src\\repositories\\permission_repo.rs", "source_location": "L95"}]}