{"nodes": [{"id": "e_work_abt_abt_core_src_shared_identity_permission_cache_rs", "label": "permission_cache.rs", "file_type": "code", "source_file": "E:\\work\\abt\\abt-core\\src\\shared\\identity\\permission_cache.rs", "source_location": "L1"}, {"id": "identity_permission_cache_cachestate", "label": "CacheState", "file_type": "code", "source_file": "E:\\work\\abt\\abt-core\\src\\shared\\identity\\permission_cache.rs", "source_location": "L13"}, {"id": "identity_permission_cache_cachestate_new", "label": ".new()", "file_type": "code", "source_file": "E:\\work\\abt\\abt-core\\src\\shared\\identity\\permission_cache.rs", "source_location": "L19"}, {"id": "identity_permission_cache_cachestate_is_stale", "label": ".is_stale()", "file_type": "code", "source_file": "E:\\work\\abt\\abt-core\\src\\shared\\identity\\permission_cache.rs", "source_location": "L26"}, {"id": "identity_permission_cache_rolepermissioncache", "label": "RolePermissionCache", "file_type": "code", "source_file": "E:\\work\\abt\\abt-core\\src\\shared\\identity\\permission_cache.rs", "source_location": "L32"}, {"id": "identity_permission_cache_rolepermissioncache_new", "label": ".new()", "file_type": "code", "source_file": "E:\\work\\abt\\abt-core\\src\\shared\\identity\\permission_cache.rs", "source_location": "L38"}, {"id": "identity_permission_cache_rolepermissioncache_load", "label": ".load()", "file_type": "code", "source_file": "E:\\work\\abt\\abt-core\\src\\shared\\identity\\permission_cache.rs", "source_location": "L47"}, {"id": "identity_permission_cache_rolepermissioncache_ensure_fresh", "label": ".ensure_fresh()", "file_type": "code", "source_file": "E:\\work\\abt\\abt-core\\src\\shared\\identity\\permission_cache.rs", "source_location": "L96"}, {"id": "identity_permission_cache_rolepermissioncache_get_merged_permissions", "label": ".get_merged_permissions()", "file_type": "code", "source_file": "E:\\work\\abt\\abt-core\\src\\shared\\identity\\permission_cache.rs", "source_location": "L104"}, {"id": "identity_permission_cache_rolepermissioncache_has_permission", "label": ".has_permission()", "file_type": "code", "source_file": "E:\\work\\abt\\abt-core\\src\\shared\\identity\\permission_cache.rs", "source_location": "L117"}, {"id": "identity_permission_cache_rolepermissioncache_reload", "label": ".reload()", "file_type": "code", "source_file": "E:\\work\\abt\\abt-core\\src\\shared\\identity\\permission_cache.rs", "source_location": "L124"}, {"id": "identity_permission_cache_rolepermissioncache_resolve_dfs", "label": ".resolve_dfs()", "file_type": "code", "source_file": "E:\\work\\abt\\abt-core\\src\\shared\\identity\\permission_cache.rs", "source_location": "L132"}, {"id": "identity_permission_cache_make_test_cache", "label": "make_test_cache()", "file_type": "code", "source_file": "E:\\work\\abt\\abt-core\\src\\shared\\identity\\permission_cache.rs", "source_location": "L174"}, {"id": "identity_permission_cache_test_empty_cache", "label": "test_empty_cache()", "file_type": "code", "source_file": "E:\\work\\abt\\abt-core\\src\\shared\\identity\\permission_cache.rs", "source_location": "L181"}, {"id": "identity_permission_cache_test_has_permission_empty", "label": "test_has_permission_empty()", "file_type": "code", "source_file": "E:\\work\\abt\\abt-core\\src\\shared\\identity\\permission_cache.rs", "source_location": "L188"}, {"id": "identity_permission_cache_test_manual_cache_population", "label": "test_manual_cache_population()", "file_type": "code", "source_file": "E:\\work\\abt\\abt-core\\src\\shared\\identity\\permission_cache.rs", "source_location": "L194"}, {"id": "identity_permission_cache_test_merged_permissions_multiple_roles", "label": "test_merged_permissions_multiple_roles()", "file_type": "code", "source_file": "E:\\work\\abt\\abt-core\\src\\shared\\identity\\permission_cache.rs", "source_location": "L208"}], "edges": [{"source": "e_work_abt_abt_core_src_shared_identity_permission_cache_rs", "target": "collections", "relation": "imports_from", "confidence": "EXTRACTED", "source_file": "E:\\work\\abt\\abt-core\\src\\shared\\identity\\permission_cache.rs", "source_location": "L1", "weight": 1.0, "context": "import"}, {"source": "e_work_abt_abt_core_src_shared_identity_permission_cache_rs", "target": "arc", "relation": "imports_from", "confidence": "EXTRACTED", "source_file": "E:\\work\\abt\\abt-core\\src\\shared\\identity\\permission_cache.rs", "source_location": "L2", "weight": 1.0, "context": "import"}, {"source": "e_work_abt_abt_core_src_shared_identity_permission_cache_rs", "target": "instant", "relation": "imports_from", "confidence": "EXTRACTED", "source_file": "E:\\work\\abt\\abt-core\\src\\shared\\identity\\permission_cache.rs", "source_location": "L3", "weight": 1.0, "context": "import"}, {"source": "e_work_abt_abt_core_src_shared_identity_permission_cache_rs", "target": "pgpool", "relation": "imports_from", "confidence": "EXTRACTED", "source_file": "E:\\work\\abt\\abt-core\\src\\shared\\identity\\permission_cache.rs", "source_location": "L5", "weight": 1.0, "context": "import"}, {"source": "e_work_abt_abt_core_src_shared_identity_permission_cache_rs", "target": "rwlock", "relation": "imports_from", "confidence": "EXTRACTED", "source_file": "E:\\work\\abt\\abt-core\\src\\shared\\identity\\permission_cache.rs", "source_location": "L6", "weight": 1.0, "context": "import"}, {"source": "e_work_abt_abt_core_src_shared_identity_permission_cache_rs", "target": "identityrepo", "relation": "imports_from", "confidence": "EXTRACTED", "source_file": "E:\\work\\abt\\abt-core\\src\\shared\\identity\\permission_cache.rs", "source_location": "L8", "weight": 1.0, "context": "import"}, {"source": "e_work_abt_abt_core_src_shared_identity_permission_cache_rs", "target": "identity_permission_cache_cachestate", "relation": "contains", "confidence": "EXTRACTED", "source_file": "E:\\work\\abt\\abt-core\\src\\shared\\identity\\permission_cache.rs", "source_location": "L13", "weight": 1.0}, {"source": "identity_permission_cache_cachestate", "target": "identity_permission_cache_cachestate_new", "relation": "method", "confidence": "EXTRACTED", "source_file": "E:\\work\\abt\\abt-core\\src\\shared\\identity\\permission_cache.rs", "source_location": "L19", "weight": 1.0}, {"source": "identity_permission_cache_cachestate", "target": "identity_permission_cache_cachestate_is_stale", "relation": "method", "confidence": "EXTRACTED", "source_file": "E:\\work\\abt\\abt-core\\src\\shared\\identity\\permission_cache.rs", "source_location": "L26", "weight": 1.0}, {"source": "e_work_abt_abt_core_src_shared_identity_permission_cache_rs", "target": "identity_permission_cache_rolepermissioncache", "relation": "contains", "confidence": "EXTRACTED", "source_file": "E:\\work\\abt\\abt-core\\src\\shared\\identity\\permission_cache.rs", "source_location": "L32", "weight": 1.0}, {"source": "identity_permission_cache_rolepermissioncache", "target": "identity_permission_cache_rolepermissioncache_new", "relation": "method", "confidence": "EXTRACTED", "source_file": "E:\\work\\abt\\abt-core\\src\\shared\\identity\\permission_cache.rs", "source_location": "L38", "weight": 1.0}, {"source": "identity_permission_cache_rolepermissioncache", "target": "identity_permission_cache_rolepermissioncache_load", "relation": "method", "confidence": "EXTRACTED", "source_file": "E:\\work\\abt\\abt-core\\src\\shared\\identity\\permission_cache.rs", "source_location": "L47", "weight": 1.0}, {"source": "identity_permission_cache_rolepermissioncache", "target": "identity_permission_cache_rolepermissioncache_ensure_fresh", "relation": "method", "confidence": "EXTRACTED", "source_file": "E:\\work\\abt\\abt-core\\src\\shared\\identity\\permission_cache.rs", "source_location": "L96", "weight": 1.0}, {"source": "identity_permission_cache_rolepermissioncache", "target": "identity_permission_cache_rolepermissioncache_get_merged_permissions", "relation": "method", "confidence": "EXTRACTED", "source_file": "E:\\work\\abt\\abt-core\\src\\shared\\identity\\permission_cache.rs", "source_location": "L104", "weight": 1.0}, {"source": "identity_permission_cache_rolepermissioncache", "target": "identity_permission_cache_rolepermissioncache_has_permission", "relation": "method", "confidence": "EXTRACTED", "source_file": "E:\\work\\abt\\abt-core\\src\\shared\\identity\\permission_cache.rs", "source_location": "L117", "weight": 1.0}, {"source": "identity_permission_cache_rolepermissioncache", "target": "identity_permission_cache_rolepermissioncache_reload", "relation": "method", "confidence": "EXTRACTED", "source_file": "E:\\work\\abt\\abt-core\\src\\shared\\identity\\permission_cache.rs", "source_location": "L124", "weight": 1.0}, {"source": "identity_permission_cache_rolepermissioncache", "target": "identity_permission_cache_rolepermissioncache_resolve_dfs", "relation": "method", "confidence": "EXTRACTED", "source_file": "E:\\work\\abt\\abt-core\\src\\shared\\identity\\permission_cache.rs", "source_location": "L132", "weight": 1.0}, {"source": "e_work_abt_abt_core_src_shared_identity_permission_cache_rs", "target": "super", "relation": "imports_from", "confidence": "EXTRACTED", "source_file": "E:\\work\\abt\\abt-core\\src\\shared\\identity\\permission_cache.rs", "source_location": "L172", "weight": 1.0, "context": "import"}, {"source": "e_work_abt_abt_core_src_shared_identity_permission_cache_rs", "target": "identity_permission_cache_make_test_cache", "relation": "contains", "confidence": "EXTRACTED", "source_file": "E:\\work\\abt\\abt-core\\src\\shared\\identity\\permission_cache.rs", "source_location": "L174", "weight": 1.0}, {"source": "e_work_abt_abt_core_src_shared_identity_permission_cache_rs", "target": "identity_permission_cache_test_empty_cache", "relation": "contains", "confidence": "EXTRACTED", "source_file": "E:\\work\\abt\\abt-core\\src\\shared\\identity\\permission_cache.rs", "source_location": "L181", "weight": 1.0}, {"source": "e_work_abt_abt_core_src_shared_identity_permission_cache_rs", "target": "identity_permission_cache_test_has_permission_empty", "relation": "contains", "confidence": "EXTRACTED", "source_file": "E:\\work\\abt\\abt-core\\src\\shared\\identity\\permission_cache.rs", "source_location": "L188", "weight": 1.0}, {"source": "e_work_abt_abt_core_src_shared_identity_permission_cache_rs", "target": "identity_permission_cache_test_manual_cache_population", "relation": "contains", "confidence": "EXTRACTED", "source_file": "E:\\work\\abt\\abt-core\\src\\shared\\identity\\permission_cache.rs", "source_location": "L194", "weight": 1.0}, {"source": "e_work_abt_abt_core_src_shared_identity_permission_cache_rs", "target": "identity_permission_cache_test_merged_permissions_multiple_roles", "relation": "contains", "confidence": "EXTRACTED", "source_file": "E:\\work\\abt\\abt-core\\src\\shared\\identity\\permission_cache.rs", "source_location": "L208", "weight": 1.0}, {"source": "identity_permission_cache_rolepermissioncache_load", "target": "identity_permission_cache_rolepermissioncache_new", "relation": "calls", "context": "call", "confidence": "EXTRACTED", "source_file": "E:\\work\\abt\\abt-core\\src\\shared\\identity\\permission_cache.rs", "source_location": "L66", "weight": 1.0}, {"source": "identity_permission_cache_rolepermissioncache_load", "target": "identity_permission_cache_rolepermissioncache_resolve_dfs", "relation": "calls", "context": "call", "confidence": "EXTRACTED", "source_file": "E:\\work\\abt\\abt-core\\src\\shared\\identity\\permission_cache.rs", "source_location": "L78", "weight": 1.0}, {"source": "identity_permission_cache_rolepermissioncache_ensure_fresh", "target": "identity_permission_cache_cachestate_is_stale", "relation": "calls", "context": "call", "confidence": "EXTRACTED", "source_file": "E:\\work\\abt\\abt-core\\src\\shared\\identity\\permission_cache.rs", "source_location": "L97", "weight": 1.0}, {"source": "identity_permission_cache_rolepermissioncache_ensure_fresh", "target": "identity_permission_cache_rolepermissioncache_load", "relation": "calls", "context": "call", "confidence": "EXTRACTED", "source_file": "E:\\work\\abt\\abt-core\\src\\shared\\identity\\permission_cache.rs", "source_location": "L98", "weight": 1.0}, {"source": "identity_permission_cache_rolepermissioncache_get_merged_permissions", "target": "identity_permission_cache_rolepermissioncache_ensure_fresh", "relation": "calls", "context": "call", "confidence": "EXTRACTED", "source_file": "E:\\work\\abt\\abt-core\\src\\shared\\identity\\permission_cache.rs", "source_location": "L105", "weight": 1.0}, {"source": "identity_permission_cache_rolepermissioncache_get_merged_permissions", "target": "identity_permission_cache_rolepermissioncache_new", "relation": "calls", "context": "call", "confidence": "EXTRACTED", "source_file": "E:\\work\\abt\\abt-core\\src\\shared\\identity\\permission_cache.rs", "source_location": "L107", "weight": 1.0}, {"source": "identity_permission_cache_rolepermissioncache_has_permission", "target": "identity_permission_cache_rolepermissioncache_get_merged_permissions", "relation": "calls", "context": "call", "confidence": "EXTRACTED", "source_file": "E:\\work\\abt\\abt-core\\src\\shared\\identity\\permission_cache.rs", "source_location": "L118", "weight": 1.0}, {"source": "identity_permission_cache_rolepermissioncache_reload", "target": "identity_permission_cache_rolepermissioncache_load", "relation": "calls", "context": "call", "confidence": "EXTRACTED", "source_file": "E:\\work\\abt\\abt-core\\src\\shared\\identity\\permission_cache.rs", "source_location": "L125", "weight": 1.0}, {"source": "identity_permission_cache_make_test_cache", "target": "identity_permission_cache_rolepermissioncache_new", "relation": "calls", "context": "call", "confidence": "EXTRACTED", "source_file": "E:\\work\\abt\\abt-core\\src\\shared\\identity\\permission_cache.rs", "source_location": "L176", "weight": 1.0}, {"source": "identity_permission_cache_test_empty_cache", "target": "identity_permission_cache_make_test_cache", "relation": "calls", "context": "call", "confidence": "EXTRACTED", "source_file": "E:\\work\\abt\\abt-core\\src\\shared\\identity\\permission_cache.rs", "source_location": "L182", "weight": 1.0}, {"source": "identity_permission_cache_test_empty_cache", "target": "identity_permission_cache_rolepermissioncache_get_merged_permissions", "relation": "calls", "context": "call", "confidence": "EXTRACTED", "source_file": "E:\\work\\abt\\abt-core\\src\\shared\\identity\\permission_cache.rs", "source_location": "L183", "weight": 1.0}, {"source": "identity_permission_cache_test_has_permission_empty", "target": "identity_permission_cache_make_test_cache", "relation": "calls", "context": "call", "confidence": "EXTRACTED", "source_file": "E:\\work\\abt\\abt-core\\src\\shared\\identity\\permission_cache.rs", "source_location": "L189", "weight": 1.0}, {"source": "identity_permission_cache_test_manual_cache_population", "target": "identity_permission_cache_make_test_cache", "relation": "calls", "context": "call", "confidence": "EXTRACTED", "source_file": "E:\\work\\abt\\abt-core\\src\\shared\\identity\\permission_cache.rs", "source_location": "L195", "weight": 1.0}, {"source": "identity_permission_cache_test_manual_cache_population", "target": "identity_permission_cache_rolepermissioncache_new", "relation": "calls", "context": "call", "confidence": "EXTRACTED", "source_file": "E:\\work\\abt\\abt-core\\src\\shared\\identity\\permission_cache.rs", "source_location": "L198", "weight": 1.0}, {"source": "identity_permission_cache_test_merged_permissions_multiple_roles", "target": "identity_permission_cache_make_test_cache", "relation": "calls", "context": "call", "confidence": "EXTRACTED", "source_file": "E:\\work\\abt\\abt-core\\src\\shared\\identity\\permission_cache.rs", "source_location": "L209", "weight": 1.0}, {"source": "identity_permission_cache_test_merged_permissions_multiple_roles", "target": "identity_permission_cache_rolepermissioncache_new", "relation": "calls", "context": "call", "confidence": "EXTRACTED", "source_file": "E:\\work\\abt\\abt-core\\src\\shared\\identity\\permission_cache.rs", "source_location": "L211", "weight": 1.0}, {"source": "identity_permission_cache_test_merged_permissions_multiple_roles", "target": "identity_permission_cache_rolepermissioncache_get_merged_permissions", "relation": "calls", "context": "call", "confidence": "EXTRACTED", "source_file": "E:\\work\\abt\\abt-core\\src\\shared\\identity\\permission_cache.rs", "source_location": "L220", "weight": 1.0}], "raw_calls": [{"caller_nid": "identity_permission_cache_cachestate_is_stale", "callee": "as_secs", "is_member_call": true, "source_file": "E:\\work\\abt\\abt-core\\src\\shared\\identity\\permission_cache.rs", "source_location": "L27"}, {"caller_nid": "identity_permission_cache_cachestate_is_stale", "callee": "elapsed", "is_member_call": true, "source_file": "E:\\work\\abt\\abt-core\\src\\shared\\identity\\permission_cache.rs", "source_location": "L27"}, {"caller_nid": "identity_permission_cache_rolepermissioncache_load", "callee": "map_err", "is_member_call": true, "source_file": "E:\\work\\abt\\abt-core\\src\\shared\\identity\\permission_cache.rs", "source_location": "L48"}, {"caller_nid": "identity_permission_cache_rolepermissioncache_load", "callee": "acquire", "is_member_call": true, "source_file": "E:\\work\\abt\\abt-core\\src\\shared\\identity\\permission_cache.rs", "source_location": "L48"}, {"caller_nid": "identity_permission_cache_rolepermissioncache_load", "callee": "map_err", "is_member_call": true, "source_file": "E:\\work\\abt\\abt-core\\src\\shared\\identity\\permission_cache.rs", "source_location": "L54"}, {"caller_nid": "identity_permission_cache_rolepermissioncache_load", "callee": "map_err", "is_member_call": true, "source_file": "E:\\work\\abt\\abt-core\\src\\shared\\identity\\permission_cache.rs", "source_location": "L59"}, {"caller_nid": "identity_permission_cache_rolepermissioncache_load", "callee": "into_iter", "is_member_call": true, "source_file": "E:\\work\\abt\\abt-core\\src\\shared\\identity\\permission_cache.rs", "source_location": "L63"}, {"caller_nid": "identity_permission_cache_rolepermissioncache_load", "callee": "or_default", "is_member_call": true, "source_file": "E:\\work\\abt\\abt-core\\src\\shared\\identity\\permission_cache.rs", "source_location": "L69"}, {"caller_nid": "identity_permission_cache_rolepermissioncache_load", "callee": "entry", "is_member_call": true, "source_file": "E:\\work\\abt\\abt-core\\src\\shared\\identity\\permission_cache.rs", "source_location": "L69"}, {"caller_nid": "identity_permission_cache_rolepermissioncache_load", "callee": "keys", "is_member_call": true, "source_file": "E:\\work\\abt\\abt-core\\src\\shared\\identity\\permission_cache.rs", "source_location": "L77"}, {"caller_nid": "identity_permission_cache_rolepermissioncache_get_merged_permissions", "callee": "extend", "is_member_call": true, "source_file": "E:\\work\\abt\\abt-core\\src\\shared\\identity\\permission_cache.rs", "source_location": "L110"}, {"caller_nid": "identity_permission_cache_rolepermissioncache_get_merged_permissions", "callee": "cloned", "is_member_call": true, "source_file": "E:\\work\\abt\\abt-core\\src\\shared\\identity\\permission_cache.rs", "source_location": "L110"}, {"caller_nid": "identity_permission_cache_rolepermissioncache_resolve_dfs", "callee": "unwrap_or_default", "is_member_call": true, "source_file": "E:\\work\\abt\\abt-core\\src\\shared\\identity\\permission_cache.rs", "source_location": "L152"}, {"caller_nid": "identity_permission_cache_rolepermissioncache_resolve_dfs", "callee": "cloned", "is_member_call": true, "source_file": "E:\\work\\abt\\abt-core\\src\\shared\\identity\\permission_cache.rs", "source_location": "L152"}, {"caller_nid": "identity_permission_cache_rolepermissioncache_resolve_dfs", "callee": "extend", "is_member_call": true, "source_file": "E:\\work\\abt\\abt-core\\src\\shared\\identity\\permission_cache.rs", "source_location": "L159"}, {"caller_nid": "identity_permission_cache_rolepermissioncache_resolve_dfs", "callee": "cloned", "is_member_call": true, "source_file": "E:\\work\\abt\\abt-core\\src\\shared\\identity\\permission_cache.rs", "source_location": "L159"}, {"caller_nid": "identity_permission_cache_test_manual_cache_population", "callee": "drop", "is_member_call": false, "source_file": "E:\\work\\abt\\abt-core\\src\\shared\\identity\\permission_cache.rs", "source_location": "L201"}, {"caller_nid": "identity_permission_cache_test_merged_permissions_multiple_roles", "callee": "drop", "is_member_call": false, "source_file": "E:\\work\\abt\\abt-core\\src\\shared\\identity\\permission_cache.rs", "source_location": "L218"}]}