{
  "db_name": "PostgreSQL",
  "query": "\n            SELECT COUNT(*) FROM document_links\n            WHERE (source_type = $1 AND source_id = $2)\n               OR (target_type = $1 AND target_id = $2)\n            ",
  "describe": {
    "columns": [
      {
        "ordinal": 0,
        "name": "count",
        "type_info": "Int8",
        "origin": "Expression"
      }
    ],
    "parameters": {
      "Left": [
        "Int2",
        "Int8"
      ]
    },
    "nullable": [
      null
    ]
  },
  "hash": "7e1e0a2908a6165ca6001255f1fbd531930c75feb4d37d24fe25778749502c54"
}
